dagster_airflow/__init__.py
dagster_airflow/airflow_dag_converter.py
dagster_airflow/dagster_asset_factory.py
dagster_airflow/dagster_factory.py
dagster_airflow/dagster_job_factory.py
dagster_airflow/dagster_schedule_factory.py
dagster_airflow/patch_airflow_example_dag.py
dagster_airflow/py.typed
dagster_airflow/utils.py
dagster_airflow/version.py
dagster_airflow/hooks/__init__.py
dagster_airflow/hooks/dagster_hook.py
dagster_airflow/links/__init__.py
dagster_airflow/links/dagster_link.py
dagster_airflow/operators/__init__.py
dagster_airflow/operators/dagster_operator.py
dagster_airflow/resources/__init__.py
dagster_airflow/resources/airflow_db.py
dagster_airflow/resources/airflow_ephemeral_db.py
dagster_airflow/resources/airflow_persistent_db.py
dagster_airflow-1.12.13.dist-info/licenses/LICENSE
dagster_airflow-1.12.13.dist-info/METADATA
dagster_airflow-1.12.13.dist-info/WHEEL
dagster_airflow-1.12.13.dist-info/entry_points.txt
dagster_airflow-1.12.13.dist-info/top_level.txt
dagster_airflow-1.12.13.dist-info/RECORD
